{
  "$schema": "http://solettaproject.github.io/soletta/schemas/node-type-genspec.schema",
  "name": "flower-power",
  "meta": {
    "author": "Intel Corporation",
    "license": "BSD-3-Clause",
    "version": "1"
  },
  "types": [
    {
      "category": "iot/cloud",
      "description": "Fetch plants Flower-Power data via HTTP",
      "in_ports": [
       {
         "data_type": "any",
         "description": "Fetch plants data via HTTP. Username and password must be provided before otherwise an error packet will be sent.",
         "methods": {
           "process": "http_get_process"
         },
         "name": "GET",
         "required": true
       },
       {
         "data_type": "string",
         "description": "Username to be used to get plants information. It must be previously registered at Parrot site or app.",
         "methods": {
           "process": "http_set_username"
         },
         "name": "USERNAME",
         "required": true
       },
       {
         "data_type": "string",
         "description": "Password for username to be used to get plants information.",
         "methods": {
           "process": "http_set_password"
         },
         "name": "PASSWORD",
         "required": true
       }
      ],
      "methods": {
        "open": "http_get_open",
        "close": "http_get_close"
      },
      "name": "flower-power/http-get",
      "options": {
        "members": [
          {
            "data_type": "string",
            "description": "Parrot client id",
            "name": "client_id"
          },
          {
            "data_type": "string",
            "description": "Parrot client secret",
            "name": "client_secret"
          }
        ],
        "version": 1
      },
      "out_ports": [
        {
          "data_type": "custom:PACKET_TYPE_FLOWER_POWER",
          "description": "Packet with measures (sunlight, temperature, soil moisture and fertilizer) and thresholds related to a plant.",
          "name": "OUT"
        },
        {
          "data_type": "custom:PACKET_TYPE_FLOWER_POWER_SENSOR",
          "description": "Packet with sensor information, as battery level and battery's end of life date.",
          "name": "DEVICE_INFO"
        }
      ],
      "private_data_type": "http_get_data",
      "url": "http://solettaproject.org/doc/latest/node_types/flower-power/http-get.html"
    },
    {
      "category": "iot/cloud",
      "description": "Parse Flower-Power packets splitting into each measure.",
      "in_ports": [
       {
          "data_type": "custom:PACKET_TYPE_FLOWER_POWER",
          "description": "Packet with measures (sunlight, temperature, soil moisture and fertilizer) and thresholds related to a plant.",
         "methods": {
           "process": "parse_packet"
         },
         "name": "IN",
         "required": true
       }
      ],
      "name": "flower-power/get-value",
      "out_ports": [
        {
          "data_type": "string",
          "description": "Plant identification, also known as location identifier.",
          "name": "ID"
        },
        {
          "data_type": "float",
          "description": "Plant's fertilizer level in mS/cm. The typical range for fertilizer in horticultural applications is 0 to 4 mS/cm. Generally, fertilizer < 1 is low, fertilizer in the range of 1 - 3 is a good range, above 3 is high, and above 4 may to too high. Fertilizer usage and sensitivity is plant specific.",
          "name": "FERTILIZER"
        },
        {
          "data_type": "float",
          "description": "Plant's fertilizer minimum threshold.",
          "name": "FERTILIZER_MIN"
        },
        {
          "data_type": "float",
          "description": "Plant's fertilizer maximum threshold.",
          "name": "FERTILIZER_MAX"
        },
        {
          "data_type": "float",
          "description": "Plant's sunlight level in Daily Light Integral (DLI) - mole x m-2 x d-1.",
          "name": "LIGHT"
        },
        {
          "data_type": "float",
          "description": "Plant's sunlight minimum threshold.",
          "name": "LIGHT_MIN"
        },
        {
          "data_type": "float",
          "description": "Plant's sunlight maximum threshold.",
          "name": "LIGHT_MAX"
        },
        {
          "data_type": "float",
          "description": "Air temperature around the plant in Kelvin. The range of temperature that is generally comfortable for most plants is between 283-305K.",
          "name": "KELVIN"
        },
        {
          "data_type": "float",
          "description": "Minimum threshold for air temperature around the plant(in Kelvin).",
          "name": "KELVIN_MIN"
        },
        {
          "data_type": "float",
          "description": "Maximum threshold for air temperature around the plant(in Kelvin).",
          "name": "KELVIN_MAX"
        },
        {
          "data_type": "timestamp",
          "description": "Timestamp of sensors reading.",
          "name": "TIMESTAMP"
        },
        {
          "data_type": "float",
          "description": "Plant's water lever (soil moisture) in a range from 0 to 50%. The typical soil moisture range is between 8 (very dry) to 45 (saturated). The soil moisture will read 0 when in air. Generally, most plants require watering when the soil moisture is in the range of 12 to 18. If the soil moisture stays > 40 for too long, this may be harmful to some plants",
          "name": "WATER"
        },
        {
          "data_type": "float",
          "description": "Plant's water minimum threshold.",
          "name": "WATER_MIN"
        },
        {
          "data_type": "float",
          "description": "Plant's water maximum threshold.",
          "name": "WATER_MAX"
        }
      ],
      "url": "http://solettaproject.org/doc/latest/node_types/flower-power/get-value.html"
    },
    {
      "category": "iot/cloud",
      "description": "Filter Flower-Power packets, forwarding only packets that matches a specific plant ID.",
      "in_ports": [
       {
          "data_type": "custom:PACKET_TYPE_FLOWER_POWER",
          "description": "Packet with measures (sunlight, temperature, soil moisture and fertilizer) and thresholds related to a plant.",
         "methods": {
           "process": "filter_packet"
         },
         "name": "IN",
         "required": true
       },
       {
         "data_type": "string",
         "description": "Plant identification, also known as location identifier. Overwrite previous ID or ID set via options.",
         "methods": {
           "process": "filter_set_id"
         },
         "name": "ID"
       }
      ],
      "methods": {
        "open": "filter_open",
        "close": "filter_close"
      },
      "name": "flower-power/filter-id",
      "options": {
        "members": [
          {
            "data_type": "string",
            "default": null,
            "description": "Plant identifier.",
            "name": "id"
          }
        ],
        "version": 1
      },
      "out_ports": [
        {
          "data_type": "custom:PACKET_TYPE_FLOWER_POWER",
          "description": "Packet with measures (sunlight, temperature, soil moisture and fertilizer) and thresholds related to the plant specified by options ID.",
          "name": "OUT",
          "required": true
        }
      ],
      "private_data_type": "filter_data",
      "url": "http://solettaproject.org/doc/latest/node_types/flower-power/filter-id.html"
    },
    {
      "category": "iot/cloud",
      "description": "Parse Flower-Power sensor packets splitting into each measure.",
      "in_ports": [
       {
          "data_type": "custom:PACKET_TYPE_FLOWER_POWER_SENSOR",
          "description": "Packet with sensor information, as battery level and battery's end of life date related to a sensor.",
          "methods": {
            "process": "parse_sensor_packet"
          },
          "name": "IN",
          "required": true
       }
      ],
      "name": "flower-power/get-sensor-value",
      "out_ports": [
        {
          "data_type": "string",
          "description": "Sensor identification, also known as sensor serial.",
          "name": "ID"
        },
        {
          "data_type": "float",
          "description": "Battery level (percent).",
          "name": "BATTERY_LEVEL"
        },
        {
          "data_type": "timestamp",
          "description": "Timestamp of estimated battery end of life.",
          "name": "BATTERY_END_OF_LIFE"
        },
        {
          "data_type": "timestamp",
          "description": "Timestamp of sensors reading.",
          "name": "TIMESTAMP"
        }
      ],
      "url": "http://solettaproject.org/doc/latest/node_types/flower-power/get-sensor-value.html"
    },
    {
      "category": "iot/cloud",
      "description": "Filter Flower-Power device information packets, forwarding only packets that matches a specific sensor ID.",
      "in_ports": [
       {
          "data_type": "custom:PACKET_TYPE_FLOWER_POWER_SENSOR",
          "description": "Packet with sensor information, as battery level and battery's end of life date.",
         "methods": {
           "process": "filter_sensor_packet"
         },
         "name": "IN",
         "required": true
       },
       {
         "data_type": "string",
         "description": "Sensor identification, also known as sensor serial. Overwrite previous ID or ID set via options.",
         "methods": {
           "process": "filter_set_id"
         },
         "name": "ID"
       }
      ],
      "methods": {
        "open": "filter_open",
        "close": "filter_close"
      },
      "name": "flower-power/filter-sensor-id",
      "options": {
        "members": [
          {
            "data_type": "string",
            "default": null,
            "description": "Sensor identifier.",
            "name": "id"
          }
        ],
        "version": 1
      },
      "out_ports": [
        {
          "data_type": "custom:PACKET_TYPE_FLOWER_POWER_SENSOR",
          "description": "Packet with sensor information, as battery level and battery's end of life date related to the sensor specified by options ID.",
          "name": "OUT",
          "required": true
        }
      ],
      "private_data_type": "filter_data",
      "url": "http://solettaproject.org/doc/latest/node_types/flower-power/filter-sensor-id.html"
    }
  ]
}
